siddarth/sin.v
module tb;

    // Inputs
    reg Clk;
    reg en;
    reg reset;

    // Outputs
    wire signed [7:0] data_out;
   // wire signed [7:0] data_out2;

    // Instantiate the Unit Under Test (UUT)
    //sin_wave_gen inst(Clk, data_out);
     sine_wave_gen uut (
         .Clk(Clk),
         .data_out(data_out)
     );

    //Generate a clock with 10 ns clock period.
    initial
      begin

$dumpfile("test.vcd");
$dumpvars;
      reset = 1;
      #100;
      en = 1;
      #100;
      reset = 0;
      #100;
      reset = 1;
        Clk = 0;
        $monitor(" %b,", data_out);
        #100000 $finish;
      end
    always #5 Clk = ~Clk;

endmodule


module sine_wave_gen(Clk,data_out);
//declare input and output
    input Clk;
    output [7:0] data_out;
//declare the sine ROM - 30 registers each 8 bit wide.
    reg [7:0] sine [0:359];
//Internal signals
    integer i;
    reg [7:0] data_out;
//Initialize the sine rom with samples.
    initial begin
        i = 0;
        sine[0] = 0;
sine[1] = 1;
sine[2] = 3;
sine[3] = 5;
sine[4] = 6;
sine[5] = 8;
sine[6] = 10;
sine[7] = 12;
sine[8] = 13;
sine[9] = 15;
sine[10] = 17;
sine[11] = 19;
sine[12] = 20;
sine[13] = 22;
sine[14] = 24;
sine[15] = 25;
sine[16] = 27;
sine[17] = 29;
sine[18] = 30;
sine[19] = 32;
sine[20] = 34;
sine[21] = 35;
sine[22] = 37;
sine[23] = 39;
sine[24] = 40;
sine[25] = 42;
sine[26] = 43;
sine[27] = 45;
sine[28] = 46;
sine[29] = 48;
sine[30] = 49;
sine[31] = 51;
sine[32] = 52;
sine[33] = 54;
sine[34] = 55;
sine[35] = 57;
sine[36] = 58;
sine[37] = 60;
sine[38] = 61;
sine[39] = 62;
sine[40] = 64;
sine[41] = 65;
sine[42] = 66;
sine[43] = 68;
sine[44] = 69;
sine[45] = 70;
sine[46] = 71;
sine[47] = 73;
sine[48] = 74;
sine[49] = 75;
sine[50] = 76;
sine[51] = 77;
sine[52] = 78;
sine[53] = 79;
sine[54] = 80;
sine[55] = 81;
sine[56] = 82;
sine[57] = 83;
sine[58] = 84;
sine[59] = 85;
sine[60] = 86;
sine[61] = 87;
sine[62] = 88;
sine[63] = 89;
sine[64] = 89;
sine[65] = 90;
sine[66] = 91;
sine[67] = 92;
sine[68] = 92;
sine[69] = 93;
sine[70] = 93;
sine[71] = 94;
sine[72] = 95;
sine[73] = 95;
sine[74] = 96;
sine[75] = 96;
sine[76] = 97;
sine[77] = 97;
sine[78] = 97;
sine[79] = 98;
sine[80] = 98;
sine[81] = 98;
sine[82] = 99;
sine[83] = 99;
sine[84] = 99;
sine[85] = 99;
sine[86] = 99;
sine[87] = 99;
sine[88] = 99;
sine[89] = 99;
sine[90] = 100;
sine[91] = 99;
sine[92] = 99;
sine[93] = 99;
sine[94] = 99;
sine[95] = 99;
sine[96] = 99;
sine[97] = 99;
sine[98] = 99;
sine[99] = 98;
sine[100] = 98;
sine[101] = 98;
sine[102] = 97;
sine[103] = 97;
sine[104] = 97;
sine[105] = 96;
sine[106] = 96;
sine[107] = 95;
sine[108] = 95;
sine[109] = 94;
sine[110] = 93;
sine[111] = 93;
sine[112] = 92;
sine[113] = 92;
sine[114] = 91;
sine[115] = 90;
sine[116] = 89;
sine[117] = 89;
sine[118] = 88;
sine[119] = 87;
sine[120] = 86;
sine[121] = 85;
sine[122] = 84;
sine[123] = 83;
sine[124] = 82;
sine[125] = 81;
sine[126] = 80;
sine[127] = 79;
sine[128] = 78;
sine[129] = 77;
sine[130] = 76;
sine[131] = 75;
sine[132] = 74;
sine[133] = 73;
sine[134] = 71;
sine[135] = 70;
sine[136] = 69;
sine[137] = 68;
sine[138] = 66;
sine[139] = 65;
sine[140] = 64;
sine[141] = 62;
sine[142] = 61;
sine[143] = 60;
sine[144] = 58;
sine[145] = 57;
sine[146] = 55;
sine[147] = 54;
sine[148] = 52;
sine[149] = 51;
sine[150] = 50;
sine[151] = 48;
sine[152] = 46;
sine[153] = 45;
sine[154] = 43;
sine[155] = 42;
sine[156] = 40;
sine[157] = 39;
sine[158] = 37;
sine[159] = 35;
sine[160] = 34;
sine[161] = 32;
sine[162] = 30;
sine[163] = 29;
sine[164] = 27;
sine[165] = 25;
sine[166] = 24;
sine[167] = 22;
sine[168] = 20;
sine[169] = 19;
sine[170] = 17;
sine[171] = 15;
sine[172] = 13;
sine[173] = 12;
sine[174] = 10;
sine[175] = 8;
sine[176] = 6;
sine[177] = 5;
sine[178] = 3;
sine[179] = 1;
sine[180] = 0;
sine[181] = -1;
sine[182] = -3;
sine[183] = -5;
sine[184] = -6;
sine[185] = -8;
sine[186] = -10;
sine[187] = -12;
sine[188] = -13;
sine[189] = -15;
sine[190] = -17;
sine[191] = -19;
sine[192] = -20;
sine[193] = -22;
sine[194] = -24;
sine[195] = -25;
sine[196] = -27;
sine[197] = -29;
sine[198] = -30;
sine[199] = -32;
sine[200] = -34;
sine[201] = -35;
sine[202] = -37;
sine[203] = -39;
sine[204] = -40;
sine[205] = -42;
sine[206] = -43;
sine[207] = -45;
sine[208] = -46;
sine[209] = -48;
sine[210] = -49;
sine[211] = -51;
sine[212] = -52;
sine[213] = -54;
sine[214] = -55;
sine[215] = -57;
sine[216] = -58;
sine[217] = -60;
sine[218] = -61;
sine[219] = -62;
sine[220] = -64;
sine[221] = -65;
sine[222] = -66;
sine[223] = -68;
sine[224] = -69;
sine[225] = -70;
sine[226] = -71;
sine[227] = -73;
sine[228] = -74;
sine[229] = -75;
sine[230] = -76;
sine[231] = -77;
sine[232] = -78;
sine[233] = -79;
sine[234] = -80;
sine[235] = -81;
sine[236] = -82;
sine[237] = -83;
sine[238] = -84;
sine[239] = -85;
sine[240] = -86;
sine[241] = -87;
sine[242] = -88;
sine[243] = -89;
sine[244] = -89;
sine[245] = -90;
sine[246] = -91;
sine[247] = -92;
sine[248] = -92;
sine[249] = -93;
sine[250] = -93;
sine[251] = -94;
sine[252] = -95;
sine[253] = -95;
sine[254] = -96;
sine[255] = -96;
sine[256] = -97;
sine[257] = -97;
sine[258] = -97;
sine[259] = -98;
sine[260] = -98;
sine[261] = -98;
sine[262] = -99;
sine[263] = -99;
sine[264] = -99;
sine[265] = -99;
sine[266] = -99;
sine[267] = -99;
sine[268] = -99;
sine[269] = -99;
sine[270] = -100;
sine[271] = -99;
sine[272] = -99;
sine[273] = -99;
sine[274] = -99;
sine[275] = -99;
sine[276] = -99;
sine[277] = -99;
sine[278] = -99;
sine[279] = -98;
sine[280] = -98;
sine[281] = -98;
sine[282] = -97;
sine[283] = -97;
sine[284] = -97;
sine[285] = -96;
sine[286] = -96;
sine[287] = -95;
sine[288] = -95;
sine[289] = -94;
sine[290] = -93;
sine[291] = -93;
sine[292] = -92;
sine[293] = -92;
sine[294] = -91;
sine[295] = -90;
sine[296] = -89;
sine[297] = -89;
sine[298] = -88;
sine[299] = -87;
sine[300] = -86;
sine[301] = -85;
sine[302] = -84;
sine[303] = -83;
sine[304] = -82;
sine[305] = -81;
sine[306] = -80;
sine[307] = -79;
sine[308] = -78;
sine[309] = -77;
sine[310] = -76;
sine[311] = -75;
sine[312] = -74;
sine[313] = -73;
sine[314] = -71;
sine[315] = -70;
sine[316] = -69;
sine[317] = -68;
sine[318] = -66;
sine[319] = -65;
sine[320] = -64;
sine[321] = -62;
sine[322] = -61;
sine[323] = -60;
sine[324] = -58;
sine[325] = -57;
sine[326] = -55;
sine[327] = -54;
sine[328] = -52;
sine[329] = -51;
sine[330] = -50;
sine[331] = -48;
sine[332] = -46;
sine[333] = -45;
sine[334] = -43;
sine[335] = -42;
sine[336] = -40;
sine[337] = -39;
sine[338] = -37;
sine[339] = -35;
sine[340] = -34;
sine[341] = -32;
sine[342] = -30;
sine[343] = -29;
sine[344] = -27;
sine[345] = -25;
sine[346] = -24;
sine[347] = -22;
sine[348] = -20;
sine[349] = -19;
sine[350] = -17;
sine[351] = -15;
sine[352] = -13;
sine[353] = -12;
sine[354] = -10;
sine[355] = -8;
sine[356] = -6;
sine[357] = -5;
sine[358] = -3;
sine[359] = -1;
    end

    //At every positive edge of the clock, output a sine wave sample.
    always@ (posedge(Clk))
    begin
        data_out = sine[i];
        $display("%d    ",data_out);
        i = i+ 1;
        if(i == 359)
            i = 0;
    end

endmodule
//scale them down to -1,1
//change frequency
//create pcf file
//

siddarth/test.vcd
$date
	Fri Aug 30 16:25:05 2019
$end
$version
	Icarus Verilog
$end
$timescale
	1s
$end
$scope module tb $end
$var wire 8 ! data_out [7:0] $end
$var reg 1 " Clk $end
$var reg 1 # en $end
$var reg 1 $ reset $end
$scope module uut $end
$var wire 1 " Clk $end
$var reg 8 % data_out [7:0] $end
$var integer 32 & i [31:0] $end
$upscope $end
$upscope $end
$enddefinitions $end
#0
$dumpvars
b0 &
bx %
1$
x#
x"
bx !
$end
#100
1#
#200
0$
#300
b1 &
b0 !
b0 %
1"
1$
#305
0"
#310
b10 &
b1 !
b1 %
1"
#315
0"
#320
b11 &
b11 !
b11 %
1"
#325
0"
#330
b100 &
b101 !
b101 %
1"
#335
0"
#340
b101 &
b110 !
b110 %
1"
#345
0"
#350
b110 &
b1000 !
b1000 %
1"
#355
0"
#360
b111 &
b1010 !
b1010 %
1"
#365
0"
#370
b1000 &
b1100 !
b1100 %
1"
#375
0"
#380
b1001 &
b1101 !
b1101 %
1"
#385
0"
#390
b1010 &
b1111 !
b1111 %
1"
#395
0"
#400
b1011 &
b10001 !
b10001 %
1"
#405
0"
#410
b1100 &
b10011 !
b10011 %
1"
#415
0"
#420
b1101 &
b10100 !
b10100 %
1"
#425
0"
#430
b1110 &
b10110 !
b10110 %
1"
#435
0"
#440
b1111 &
b11000 !
b11000 %
1"
#445
0"
#450
b10000 &
b11001 !
b11001 %
1"
#455
0"
#460
b10001 &
b11011 !
b11011 %
1"
#465
0"
#470
b10010 &
b11101 !
b11101 %
1"
#475
0"
#480
b10011 &
b11110 !
b11110 %
1"
#485
0"
#490
b10100 &
b100000 !
b100000 %
1"
#495
0"
#500
b10101 &
b100010 !
b100010 %
1"
#505
0"
#510
b10110 &
b100011 !
b100011 %
1"
#515
0"
#520
b10111 &
b100101 !
b100101 %
1"
#525
0"
#530
b11000 &
b100111 !
b100111 %
1"
#535
0"
#540
b11001 &
b101000 !
b101000 %
1"
#545
0"
#550
b11010 &
b101010 !
b101010 %
1"
#555
0"
#560
b11011 &
b101011 !
b101011 %
1"
#565
0"
#570
b11100 &
b101101 !
b101101 %
1"
#575
0"
#580
b11101 &
b101110 !
b101110 %
1"
#585
0"
#590
b11110 &
b110000 !
b110000 %
1"
#595
0"
#600
b11111 &
b110001 !
b110001 %
1"
#605
0"
#610
b100000 &
b110011 !
b110011 %
1"
#615
0"
#620
b100001 &
b110100 !
b110100 %
1"
#625
0"
#630
b100010 &
b110110 !
b110110 %
1"
#635
0"
#640
b100011 &
b110111 !
b110111 %
1"
#645
0"
#650
b100100 &
b111001 !
b111001 %
1"
#655
0"
#660
b100101 &
b111010 !
b111010 %
1"
#665
0"
#670
b100110 &
b111100 !
b111100 %
1"
#675
0"
#680
b100111 &
b111101 !
b111101 %
1"
#685
0"
#690
b101000 &
b111110 !
b111110 %
1"
#695
0"
#700
b101001 &
b1000000 !
b1000000 %
1"
#705
0"
#710
b101010 &
b1000001 !
b1000001 %
1"
#715
0"
#720
b101011 &
b1000010 !
b1000010 %
1"
#725
0"
#730
b101100 &
b1000100 !
b1000100 %
1"
#735
0"
#740
b101101 &
b1000101 !
b1000101 %
1"
#745
0"
#750
b101110 &
b1000110 !
b1000110 %
1"
#755
0"
#760
b101111 &
b1000111 !
b1000111 %
1"
#765
0"
#770
b110000 &
b1001001 !
b1001001 %
1"
#775
0"
#780
b110001 &
b1001010 !
b1001010 %
1"
#785
0"
#790
b110010 &
b1001011 !
b1001011 %
1"
#795
0"
#800
b110011 &
b1001100 !
b1001100 %
1"
#805
0"
#810
b110100 &
b1001101 !
b1001101 %
1"
#815
0"
#820
b110101 &
b1001110 !
b1001110 %
1"
#825
0"
#830
b110110 &
b1001111 !
b1001111 %
1"
#835
0"
#840
b110111 &
b1010000 !
b1010000 %
1"
#845
0"
#850
b111000 &
b1010001 !
b1010001 %
1"
#855
0"
#860
b111001 &
b1010010 !
b1010010 %
1"
#865
0"
#870
b111010 &
b1010011 !
b1010011 %
1"
#875
0"
#880
b111011 &
b1010100 !
b1010100 %
1"
#885
0"
#890
b111100 &
b1010101 !
b1010101 %
1"
#895
0"
#900
b111101 &
b1010110 !
b1010110 %
1"
#905
0"
#910
b111110 &
b1010111 !
b1010111 %
1"
#915
0"
#920
b111111 &
b1011000 !
b1011000 %
1"
#925
0"
#930
b1000000 &
b1011001 !
b1011001 %
1"
#935
0"
#940
b1000001 &
1"
#945
0"
#950
b1000010 &
b1011010 !
b1011010 %
1"
#955
0"
#960
b1000011 &
b1011011 !
b1011011 %
1"
#965
0"
#970
b1000100 &
b1011100 !
b1011100 %
1"
#975
0"
#980
b1000101 &
1"
#985
0"
#990
b1000110 &
b1011101 !
b1011101 %
1"
#995
0"
#1000
b1000111 &
1"
#1005
0"
#1010
b1001000 &
b1011110 !
b1011110 %
1"
#1015
0"
#1020
b1001001 &
b1011111 !
b1011111 %
1"
#1025
0"
#1030
b1001010 &
1"
#1035
0"
#1040
b1001011 &
b1100000 !
b1100000 %
1"
#1045
0"
#1050
b1001100 &
1"
#1055
0"
#1060
b1001101 &
b1100001 !
b1100001 %
1"
#1065
0"
#1070
b1001110 &
1"
#1075
0"
#1080
b1001111 &
1"
#1085
0"
#1090
b1010000 &
b1100010 !
b1100010 %
1"
#1095
0"
#1100
b1010001 &
1"
#1105
0"
#1110
b1010010 &
1"
#1115
0"
#1120
b1010011 &
b1100011 !
b1100011 %
1"
#1125
0"
#1130
b1010100 &
1"
#1135
0"
#1140
b1010101 &
1"
#1145
0"
#1150
b1010110 &
1"
#1155
0"
#1160
b1010111 &
1"
#1165
0"
#1170
b1011000 &
1"
#1175
0"
#1180
b1011001 &
1"
#1185
0"
#1190
b1011010 &
1"
#1195
0"
#1200
b1011011 &
b1100100 !
b1100100 %
1"
#1205
0"
#1210
b1011100 &
b1100011 !
b1100011 %
1"
#1215
0"
#1220
b1011101 &
1"
#1225
0"
#1230
b1011110 &
1"
#1235
0"
#1240
b1011111 &
1"
#1245
0"
#1250
b1100000 &
1"
#1255
0"
#1260
b1100001 &
1"
#1265
0"
#1270
b1100010 &
1"
#1275
0"
#1280
b1100011 &
1"
#1285
0"
#1290
b1100100 &
b1100010 !
b1100010 %
1"
#1295
0"
#1300
b1100101 &
1"
#1305
0"
#1310
b1100110 &
1"
#1315
0"
#1320
b1100111 &
b1100001 !
b1100001 %
1"
#1325
0"
#1330
b1101000 &
1"
#1335
0"
#1340
b1101001 &
1"
#1345
0"
#1350
b1101010 &
b1100000 !
b1100000 %
1"
#1355
0"
#1360
b1101011 &
1"
#1365
0"
#1370
b1101100 &
b1011111 !
b1011111 %
1"
#1375
0"
#1380
b1101101 &
1"
#1385
0"
#1390
b1101110 &
b1011110 !
b1011110 %
1"
#1395
0"
#1400
b1101111 &
b1011101 !
b1011101 %
1"
#1405
0"
#1410
b1110000 &
1"
#1415
0"
#1420
b1110001 &
b1011100 !
b1011100 %
1"
#1425
0"
#1430
b1110010 &
1"
#1435
0"
#1440
b1110011 &
b1011011 !
b1011011 %
1"
#1445
0"
#1450
b1110100 &
b1011010 !
b1011010 %
1"
#1455
0"
#1460
b1110101 &
b1011001 !
b1011001 %
1"
#1465
0"
#1470
b1110110 &
1"
#1475
0"
#1480
b1110111 &
b1011000 !
b1011000 %
1"
#1485
0"
#1490
b1111000 &
b1010111 !
b1010111 %
1"
#1495
0"
#1500
b1111001 &
b1010110 !
b1010110 %
1"
#1505
0"
#1510
b1111010 &
b1010101 !
b1010101 %
1"
#1515
0"
#1520
b1111011 &
b1010100 !
b1010100 %
1"
#1525
0"
#1530
b1111100 &
b1010011 !
b1010011 %
1"
#1535
0"
#1540
b1111101 &
b1010010 !
b1010010 %
1"
#1545
0"
#1550
b1111110 &
b1010001 !
b1010001 %
1"
#1555
0"
#1560
b1111111 &
b1010000 !
b1010000 %
1"
#1565
0"
#1570
b10000000 &
b1001111 !
b1001111 %
1"
#1575
0"
#1580
b10000001 &
b1001110 !
b1001110 %
1"
#1585
0"
#1590
b10000010 &
b1001101 !
b1001101 %
1"
#1595
0"
#1600
b10000011 &
b1001100 !
b1001100 %
1"
#1605
0"
#1610
b10000100 &
b1001011 !
b1001011 %
1"
#1615
0"
#1620
b10000101 &
b1001010 !
b1001010 %
1"
#1625
0"
#1630
b10000110 &
b1001001 !
b1001001 %
1"
#1635
0"
#1640
b10000111 &
b1000111 !
b1000111 %
1"
#1645
0"
#1650
b10001000 &
b1000110 !
b1000110 %
1"
#1655
0"
#1660
b10001001 &
b1000101 !
b1000101 %
1"
#1665
0"
#1670
b10001010 &
b1000100 !
b1000100 %
1"
#1675
0"
#1680
b10001011 &
b1000010 !
b1000010 %
1"
#1685
0"
#1690
b10001100 &
b1000001 !
b1000001 %
1"
#1695
0"
#1700
b10001101 &
b1000000 !
b1000000 %
1"
#1705
0"
#1710
b10001110 &
b111110 !
b111110 %
1"
#1715
0"
#1720
b10001111 &
b111101 !
b111101 %
1"
#1725
0"
#1730
b10010000 &
b111100 !
b111100 %
1"
#1735
0"
#1740
b10010001 &
b111010 !
b111010 %
1"
#1745
0"
#1750
b10010010 &
b111001 !
b111001 %
1"
#1755
0"
#1760
b10010011 &
b110111 !
b110111 %
1"
#1765
0"
#1770
b10010100 &
b110110 !
b110110 %
1"
#1775
0"
#1780
b10010101 &
b110100 !
b110100 %
1"
#1785
0"
#1790
b10010110 &
b110011 !
b110011 %
1"
#1795
0"
#1800
b10010111 &
b110010 !
b110010 %
1"
#1805
0"
#1810
b10011000 &
b110000 !
b110000 %
1"
#1815
0"
#1820
b10011001 &
b101110 !
b101110 %
1"
#1825
0"
#1830
b10011010 &
b101101 !
b101101 %
1"
#1835
0"
#1840
b10011011 &
b101011 !
b101011 %
1"
#1845
0"
#1850
b10011100 &
b101010 !
b101010 %
1"
#1855
0"
#1860
b10011101 &
b101000 !
b101000 %
1"
#1865
0"
#1870
b10011110 &
b100111 !
b100111 %
1"
#1875
0"
#1880
b10011111 &
b100101 !
b100101 %
1"
#1885
0"
#1890
b10100000 &
b100011 !
b100011 %
1"
#1895
0"
#1900
b10100001 &
b100010 !
b100010 %
1"
#1905
0"
#1910
b10100010 &
b100000 !
b100000 %
1"
#1915
0"
#1920
b10100011 &
b11110 !
b11110 %
1"
#1925
0"
#1930
b10100100 &
b11101 !
b11101 %
1"
#1935
0"
#1940
b10100101 &
b11011 !
b11011 %
1"
#1945
0"
#1950
b10100110 &
b11001 !
b11001 %
1"
#1955
0"
#1960
b10100111 &
b11000 !
b11000 %
1"
#1965
0"
#1970
b10101000 &
b10110 !
b10110 %
1"
#1975
0"
#1980
b10101001 &
b10100 !
b10100 %
1"
#1985
0"
#1990
b10101010 &
b10011 !
b10011 %
1"
#1995
0"
#2000
b10101011 &
b10001 !
b10001 %
1"
#2005
0"
#2010
b10101100 &
b1111 !
b1111 %
1"
#2015
0"
#2020
b10101101 &
b1101 !
b1101 %
1"
#2025
0"
#2030
b10101110 &
b1100 !
b1100 %
1"
#2035
0"
#2040
b10101111 &
b1010 !
b1010 %
1"
#2045
0"
#2050
b10110000 &
b1000 !
b1000 %
1"
#2055
0"
#2060
b10110001 &
b110 !
b110 %
1"
#2065
0"
#2070
b10110010 &
b101 !
b101 %
1"
#2075
0"
#2080
b10110011 &
b11 !
b11 %
1"
#2085
0"
#2090
b10110100 &
b1 !
b1 %
1"
#2095
0"
#2100
b10110101 &
b0 !
b0 %
1"
#2105
0"
#2110
b10110110 &
b11111111 !
b11111111 %
1"
#2115
0"
#2120
b10110111 &
b11111101 !
b11111101 %
1"
#2125
0"
#2130
b10111000 &
b11111011 !
b11111011 %
1"
#2135
0"
#2140
b10111001 &
b11111010 !
b11111010 %
1"
#2145
0"
#2150
b10111010 &
b11111000 !
b11111000 %
1"
#2155
0"
#2160
b10111011 &
b11110110 !
b11110110 %
1"
#2165
0"
#2170
b10111100 &
b11110100 !
b11110100 %
1"
#2175
0"
#2180
b10111101 &
b11110011 !
b11110011 %
1"
#2185
0"
#2190
b10111110 &
b11110001 !
b11110001 %
1"
#2195
0"
#2200
b10111111 &
b11101111 !
b11101111 %
1"
#2205
0"
#2210
b11000000 &
b11101101 !
b11101101 %
1"
#2215
0"
#2220
b11000001 &
b11101100 !
b11101100 %
1"
#2225
0"
#2230
b11000010 &
b11101010 !
b11101010 %
1"
#2235
0"
#2240
b11000011 &
b11101000 !
b11101000 %
1"
#2245
0"
#2250
b11000100 &
b11100111 !
b11100111 %
1"
#2255
0"
#2260
b11000101 &
b11100101 !
b11100101 %
1"
#2265
0"
#2270
b11000110 &
b11100011 !
b11100011 %
1"
#2275
0"
#2280
b11000111 &
b11100010 !
b11100010 %
1"
#2285
0"
#2290
b11001000 &
b11100000 !
b11100000 %
1"
#2295
0"
#2300
b11001001 &
b11011110 !
b11011110 %
1"
#2305
0"
#2310
b11001010 &
b11011101 !
b11011101 %
1"
#2315
0"
#2320
b11001011 &
b11011011 !
b11011011 %
1"
#2325
0"
#2330
b11001100 &
b11011001 !
b11011001 %
1"
#2335
0"
#2340
b11001101 &
b11011000 !
b11011000 %
1"
#2345
0"
#2350
b11001110 &
b11010110 !
b11010110 %
1"
#2355
0"
#2360
b11001111 &
b11010101 !
b11010101 %
1"
#2365
0"
#2370
b11010000 &
b11010011 !
b11010011 %
1"
#2375
0"
#2380
b11010001 &
b11010010 !
b11010010 %
1"
#2385
0"
#2390
b11010010 &
b11010000 !
b11010000 %
1"
#2395
0"
#2400
b11010011 &
b11001111 !
b11001111 %
1"
#2405
0"
#2410
b11010100 &
b11001101 !
b11001101 %
1"
#2415
0"
#2420
b11010101 &
b11001100 !
b11001100 %
1"
#2425
0"
#2430
b11010110 &
b11001010 !
b11001010 %
1"
#2435
0"
#2440
b11010111 &
b11001001 !
b11001001 %
1"
#2445
0"
#2450
b11011000 &
b11000111 !
b11000111 %
1"
#2455
0"
#2460
b11011001 &
b11000110 !
b11000110 %
1"
#2465
0"
#2470
b11011010 &
b11000100 !
b11000100 %
1"
#2475
0"
#2480
b11011011 &
b11000011 !
b11000011 %
1"
#2485
0"
#2490
b11011100 &
b11000010 !
b11000010 %
1"
#2495
0"
#2500
b11011101 &
b11000000 !
b11000000 %
1"
#2505
0"
#2510
b11011110 &
b10111111 !
b10111111 %
1"
#2515
0"
#2520
b11011111 &
b10111110 !
b10111110 %
1"
#2525
0"
#2530
b11100000 &
b10111100 !
b10111100 %
1"
#2535
0"
#2540
b11100001 &
b10111011 !
b10111011 %
1"
#2545
0"
#2550
b11100010 &
b10111010 !
b10111010 %
1"
#2555
0"
#2560
b11100011 &
b10111001 !
b10111001 %
1"
#2565
0"
#2570
b11100100 &
b10110111 !
b10110111 %
1"
#2575
0"
#2580
b11100101 &
b10110110 !
b10110110 %
1"
#2585
0"
#2590
b11100110 &
b10110101 !
b10110101 %
1"
#2595
0"
#2600
b11100111 &
b10110100 !
b10110100 %
1"
#2605
0"
#2610
b11101000 &
b10110011 !
b10110011 %
1"
#2615
0"
#2620
b11101001 &
b10110010 !
b10110010 %
1"
#2625
0"
#2630
b11101010 &
b10110001 !
b10110001 %
1"
#2635
0"
#2640
b11101011 &
b10110000 !
b10110000 %
1"
#2645
0"
#2650
b11101100 &
b10101111 !
b10101111 %
1"
#2655
0"
#2660
b11101101 &
b10101110 !
b10101110 %
1"
#2665
0"
#2670
b11101110 &
b10101101 !
b10101101 %
1"
#2675
0"
#2680
b11101111 &
b10101100 !
b10101100 %
1"
#2685
0"
#2690
b11110000 &
b10101011 !
b10101011 %
1"
#2695
0"
#2700
b11110001 &
b10101010 !
b10101010 %
1"
#2705
0"
#2710
b11110010 &
b10101001 !
b10101001 %
1"
#2715
0"
#2720
b11110011 &
b10101000 !
b10101000 %
1"
#2725
0"
#2730
b11110100 &
b10100111 !
b10100111 %
1"
#2735
0"
#2740
b11110101 &
1"
#2745
0"
#2750
b11110110 &
b10100110 !
b10100110 %
1"
#2755
0"
#2760
b11110111 &
b10100101 !
b10100101 %
1"
#2765
0"
#2770
b11111000 &
b10100100 !
b10100100 %
1"
#2775
0"
#2780
b11111001 &
1"
#2785
0"
#2790
b11111010 &
b10100011 !
b10100011 %
1"
#2795
0"
#2800
b11111011 &
1"
#2805
0"
#2810
b11111100 &
b10100010 !
b10100010 %
1"
#2815
0"
#2820
b11111101 &
b10100001 !
b10100001 %
1"
#2825
0"
#2830
b11111110 &
1"
#2835
0"
#2840
b11111111 &
b10100000 !
b10100000 %
1"
#2845
0"
#2850
b100000000 &
1"
#2855
0"
#2860
b100000001 &
b10011111 !
b10011111 %
1"
#2865
0"
#2870
b100000010 &
1"
#2875
0"
#2880
b100000011 &
1"
#2885
0"
#2890
b100000100 &
b10011110 !
b10011110 %
1"
#2895
0"
#2900
b100000101 &
1"
#2905
0"
#2910
b100000110 &
1"
#2915
0"
#2920
b100000111 &
b10011101 !
b10011101 %
1"
#2925
0"
#2930
b100001000 &
1"
#2935
0"
#2940
b100001001 &
1"
#2945
0"
#2950
b100001010 &
1"
#2955
0"
#2960
b100001011 &
1"
#2965
0"
#2970
b100001100 &
1"
#2975
0"
#2980
b100001101 &
1"
#2985
0"
#2990
b100001110 &
1"
#2995
0"
#3000
b100001111 &
b10011100 !
b10011100 %
1"
#3005
0"
#3010
b100010000 &
b10011101 !
b10011101 %
1"
#3015
0"
#3020
b100010001 &
1"
#3025
0"
#3030
b100010010 &
1"
#3035
0"
#3040
b100010011 &
1"
#3045
0"
#3050
b100010100 &
1"
#3055
0"
#3060
b100010101 &
1"
#3065
0"
#3070
b100010110 &
1"
#3075
0"
#3080
b100010111 &
1"
#3085
0"
#3090
b100011000 &
b10011110 !
b10011110 %
1"
#3095
0"
#3100
b100011001 &
1"
#3105
0"
#3110
b100011010 &
1"
#3115
0"
#3120
b100011011 &
b10011111 !
b10011111 %
1"
#3125
0"
#3130
b100011100 &
1"
#3135
0"
#3140
b100011101 &
1"
#3145
0"
#3150
b100011110 &
b10100000 !
b10100000 %
1"
#3155
0"
#3160
b100011111 &
1"
#3165
0"
#3170
b100100000 &
b10100001 !
b10100001 %
1"
#3175
0"
#3180
b100100001 &
1"
#3185
0"
#3190
b100100010 &
b10100010 !
b10100010 %
1"
#3195
0"
#3200
b100100011 &
b10100011 !
b10100011 %
1"
#3205
0"
#3210
b100100100 &
1"
#3215
0"
#3220
b100100101 &
b10100100 !
b10100100 %
1"
#3225
0"
#3230
b100100110 &
1"
#3235
0"
#3240
b100100111 &
b10100101 !
b10100101 %
1"
#3245
0"
#3250
b100101000 &
b10100110 !
b10100110 %
1"
#3255
0"
#3260
b100101001 &
b10100111 !
b10100111 %
1"
#3265
0"
#3270
b100101010 &
1"
#3275
0"
#3280
b100101011 &
b10101000 !
b10101000 %
1"
#3285
0"
#3290
b100101100 &
b10101001 !
b10101001 %
1"
#3295
0"
#3300
b100101101 &
b10101010 !
b10101010 %
1"
#3305
0"
#3310
b100101110 &
b10101011 !
b10101011 %
1"
#3315
0"
#3320
b100101111 &
b10101100 !
b10101100 %
1"
#3325
0"
#3330
b100110000 &
b10101101 !
b10101101 %
1"
#3335
0"
#3340
b100110001 &
b10101110 !
b10101110 %
1"
#3345
0"
#3350
b100110010 &
b10101111 !
b10101111 %
1"
#3355
0"
#3360
b100110011 &
b10110000 !
b10110000 %
1"
#3365
0"
#3370
b100110100 &
b10110001 !
b10110001 %
1"
#3375
0"
#3380
b100110101 &
b10110010 !
b10110010 %
1"
#3385
0"
#3390
b100110110 &
b10110011 !
b10110011 %
1"
#3395
0"
#3400
b100110111 &
b10110100 !
b10110100 %
1"
#3405
0"
#3410
b100111000 &
b10110101 !
b10110101 %
1"
#3415
0"
#3420
b100111001 &
b10110110 !
b10110110 %
1"
#3425
0"
#3430
b100111010 &
b10110111 !
b10110111 %
1"
#3435
0"
#3440
b100111011 &
b10111001 !
b10111001 %
1"
#3445
0"
#3450
b100111100 &
b10111010 !
b10111010 %
1"
#3455
0"
#3460
b100111101 &
b10111011 !
b10111011 %
1"
#3465
0"
#3470
b100111110 &
b10111100 !
b10111100 %
1"
#3475
0"
#3480
b100111111 &
b10111110 !
b10111110 %
1"
#3485
0"
#3490
b101000000 &
b10111111 !
b10111111 %
1"
#3495
0"
#3500
b101000001 &
b11000000 !
b11000000 %
1"
#3505
0"
#3510
b101000010 &
b11000010 !
b11000010 %
1"
#3515
0"
#3520
b101000011 &
b11000011 !
b11000011 %
1"
#3525
0"
#3530
b101000100 &
b11000100 !
b11000100 %
1"
#3535
0"
#3540
b101000101 &
b11000110 !
b11000110 %
1"
#3545
0"
#3550
b101000110 &
b11000111 !
b11000111 %
1"
#3555
0"
#3560
b101000111 &
b11001001 !
b11001001 %
1"
#3565
0"
#3570
b101001000 &
b11001010 !
b11001010 %
1"
#3575
0"
#3580
b101001001 &
b11001100 !
b11001100 %
1"
#3585
0"
#3590
b101001010 &
b11001101 !
b11001101 %
1"
#3595
0"
#3600
b101001011 &
b11001110 !
b11001110 %
1"
#3605
0"
#3610
b101001100 &
b11010000 !
b11010000 %
1"
#3615
0"
#3620
b101001101 &
b11010010 !
b11010010 %
1"
#3625
0"
#3630
b101001110 &
b11010011 !
b11010011 %
1"
#3635
0"
#3640
b101001111 &
b11010101 !
b11010101 %
1"
#3645
0"
#3650
b101010000 &
b11010110 !
b11010110 %
1"
#3655
0"
#3660
b101010001 &
b11011000 !
b11011000 %
1"
#3665
0"
#3670
b101010010 &
b11011001 !
b11011001 %
1"
#3675
0"
